MANIFEST.in
README.rst
setup.py
django_djembe.egg-info/PKG-INFO
django_djembe.egg-info/SOURCES.txt
django_djembe.egg-info/dependency_links.txt
django_djembe.egg-info/requires.txt
django_djembe.egg-info/top_level.txt
djembe/__init__.py
djembe/admin.py
djembe/backends.py
djembe/models.py
djembe/testrunners.py
djembe/testsettings.py
djembe/migrations/0001_initial.py
djembe/migrations/__init__.py
djembe/tests/__init__.py
djembe/tests/data.py
djembe/tests/test_basics.py