Metadata-Version: 1.1
Name: django-djembe
Version: 0.2.0
Summary: 
